{
  "id": "d54296e8-bed6-4e2e-ba86-55b9e8b34310",
  "prevIds": [
    "d3efe990-05d4-41ff-b403-536896f528df"
  ],
  "version": "8",
  "dialect": "postgres",
  "ddl": [
    {
      "isRlsEnabled": false,
      "name": "access_tokens",
      "schema": "public",
      "entityType": "tables"
    },
    {
      "columns": [
        "code"
      ],
      "nameExplicit": false,
      "name": "access_tokens_pkey",
      "schema": "public",
      "table": "access_tokens",
      "entityType": "pks"
    },
    {
      "type": "text",
      "typeSchema": null,
      "notNull": true,
      "dimensions": 0,
      "default": null,
      "generated": null,
      "identity": null,
      "name": "code",
      "schema": "public",
      "table": "access_tokens",
      "entityType": "columns"
    },
    {
      "type": "uuid",
      "typeSchema": null,
      "notNull": true,
      "dimensions": 0,
      "default": null,
      "generated": null,
      "identity": null,
      "name": "application_id",
      "schema": "public",
      "table": "access_tokens",
      "entityType": "columns"
    },
    {
      "type": "uuid",
      "typeSchema": null,
      "notNull": false,
      "dimensions": 0,
      "default": null,
      "generated": null,
      "identity": null,
      "name": "account_owner_id",
      "schema": "public",
      "table": "access_tokens",
      "entityType": "columns"
    },
    {
      "type": "grant_type",
      "typeSchema": "public",
      "notNull": true,
      "dimensions": 0,
      "default": "'authorization_code'",
      "generated": null,
      "identity": null,
      "name": "grant_type",
      "schema": "public",
      "table": "access_tokens",
      "entityType": "columns"
    },
    {
      "type": "scope",
      "typeSchema": null,
      "notNull": true,
      "dimensions": 1,
      "default": null,
      "generated": null,
      "identity": null,
      "name": "scopes",
      "schema": "public",
      "table": "access_tokens",
      "entityType": "columns"
    },
    {
      "type": "timestamp with time zone",
      "typeSchema": null,
      "notNull": true,
      "dimensions": 0,
      "default": "now()",
      "generated": null,
      "identity": null,
      "name": "created",
      "schema": "public",
      "table": "access_tokens",
      "entityType": "columns"
    },
    {
      "nameExplicit": false,
      "columns": [
        "application_id"
      ],
      "schemaTo": "public",
      "tableTo": "applications",
      "columnsTo": [
        "id"
      ],
      "onUpdate": "NO ACTION",
      "onDelete": "CASCADE",
      "name": "access_tokens_application_id_applications_id_fk",
      "schema": "public",
      "table": "access_tokens",
      "entityType": "fks"
    },
    {
      "nameExplicit": false,
      "columns": [
        "account_owner_id"
      ],
      "schemaTo": "public",
      "tableTo": "account_owners",
      "columnsTo": [
        "id"
      ],
      "onUpdate": "NO ACTION",
      "onDelete": "CASCADE",
      "name": "access_tokens_account_owner_id_account_owners_id_fk",
      "schema": "public",
      "table": "access_tokens",
      "entityType": "fks"
    },
    {
      "isRlsEnabled": false,
      "name": "account_owners",
      "schema": "public",
      "entityType": "tables"
    },
    {
      "columns": [
        "id"
      ],
      "nameExplicit": false,
      "name": "account_owners_pkey",
      "schema": "public",
      "table": "account_owners",
      "entityType": "pks"
    },
    {
      "type": "uuid",
      "typeSchema": null,
      "notNull": true,
      "dimensions": 0,
      "default": null,
      "generated": null,
      "identity": null,
      "name": "id",
      "schema": "public",
      "table": "account_owners",
      "entityType": "columns"
    },
    {
      "type": "text",
      "typeSchema": null,
      "notNull": true,
      "dimensions": 0,
      "default": null,
      "generated": null,
      "identity": null,
      "name": "handle",
      "schema": "public",
      "table": "account_owners",
      "entityType": "columns"
    },
    {
      "type": "jsonb",
      "typeSchema": null,
      "notNull": true,
      "dimensions": 0,
      "default": null,
      "generated": null,
      "identity": null,
      "name": "rsa_private_key_jwk",
      "schema": "public",
      "table": "account_owners",
      "entityType": "columns"
    },
    {
      "type": "jsonb",
      "typeSchema": null,
      "notNull": true,
      "dimensions": 0,
      "default": null,
      "generated": null,
      "identity": null,
      "name": "rsa_public_key_jwk",
      "schema": "public",
      "table": "account_owners",
      "entityType": "columns"
    },
    {
      "type": "jsonb",
      "typeSchema": null,
      "notNull": true,
      "dimensions": 0,
      "default": null,
      "generated": null,
      "identity": null,
      "name": "ed25519_private_key_jwk",
      "schema": "public",
      "table": "account_owners",
      "entityType": "columns"
    },
    {
      "type": "jsonb",
      "typeSchema": null,
      "notNull": true,
      "dimensions": 0,
      "default": null,
      "generated": null,
      "identity": null,
      "name": "ed25519_public_key_jwk",
      "schema": "public",
      "table": "account_owners",
      "entityType": "columns"
    },
    {
      "type": "json",
      "typeSchema": null,
      "notNull": true,
      "dimensions": 0,
      "default": "'{}'",
      "generated": null,
      "identity": null,
      "name": "fields",
      "schema": "public",
      "table": "account_owners",
      "entityType": "columns"
    },
    {
      "type": "text",
      "typeSchema": null,
      "notNull": false,
      "dimensions": 0,
      "default": null,
      "generated": null,
      "identity": null,
      "name": "bio",
      "schema": "public",
      "table": "account_owners",
      "entityType": "columns"
    },
    {
      "type": "text",
      "typeSchema": null,
      "notNull": true,
      "dimensions": 1,
      "default": "",
      "generated": null,
      "identity": null,
      "name": "followed_tags",
      "schema": "public",
      "table": "account_owners",
      "entityType": "columns"
    },
    {
      "type": "post_visibility",
      "typeSchema": "public",
      "notNull": true,
      "dimensions": 0,
      "default": "'public'",
      "generated": null,
      "identity": null,
      "name": "visibility",
      "schema": "public",
      "table": "account_owners",
      "entityType": "columns"
    },
    {
      "type": "text",
      "typeSchema": null,
      "notNull": true,
      "dimensions": 0,
      "default": "'en'",
      "generated": null,
      "identity": null,
      "name": "language",
      "schema": "public",
      "table": "account_owners",
      "entityType": "columns"
    },
    {
      "nameExplicit": false,
      "columns": [
        "handle"
      ],
      "nullsNotDistinct": false,
      "name": "account_owners_handle_unique",
      "schema": "public",
      "table": "account_owners",
      "entityType": "uniques"
    },
    {
      "nameExplicit": false,
      "columns": [
        "id"
      ],
      "schemaTo": "public",
      "tableTo": "accounts",
      "columnsTo": [
        "id"
      ],
      "onUpdate": "NO ACTION",
      "onDelete": "CASCADE",
      "name": "account_owners_id_accounts_id_fk",
      "schema": "public",
      "table": "account_owners",
      "entityType": "fks"
    },
    {
      "isRlsEnabled": false,
      "name": "accounts",
      "schema": "public",
      "entityType": "tables"
    },
    {
      "columns": [
        "id"
      ],
      "nameExplicit": false,
      "name": "accounts_pkey",
      "schema": "public",
      "table": "accounts",
      "entityType": "pks"
    },
    {
      "type": "uuid",
      "typeSchema": null,
      "notNull": true,
      "dimensions": 0,
      "default": null,
      "generated": null,
      "identity": null,
      "name": "id",
      "schema": "public",
      "table": "accounts",
      "entityType": "columns"
    },
    {
      "type": "text",
      "typeSchema": null,
      "notNull": true,
      "dimensions": 0,
      "default": null,
      "generated": null,
      "identity": null,
      "name": "iri",
      "schema": "public",
      "table": "accounts",
      "entityType": "columns"
    },
    {
      "type": "account_type",
      "typeSchema": "public",
      "notNull": true,
      "dimensions": 0,
      "default": null,
      "generated": null,
      "identity": null,
      "name": "type",
      "schema": "public",
      "table": "accounts",
      "entityType": "columns"
    },
    {
      "type": "varchar(100)",
      "typeSchema": null,
      "notNull": true,
      "dimensions": 0,
      "default": null,
      "generated": null,
      "identity": null,
      "name": "name",
      "schema": "public",
      "table": "accounts",
      "entityType": "columns"
    },
    {
      "type": "text",
      "typeSchema": null,
      "notNull": true,
      "dimensions": 0,
      "default": null,
      "generated": null,
      "identity": null,
      "name": "handle",
      "schema": "public",
      "table": "accounts",
      "entityType": "columns"
    },
    {
      "type": "text",
      "typeSchema": null,
      "notNull": false,
      "dimensions": 0,
      "default": null,
      "generated": null,
      "identity": null,
      "name": "bio_html",
      "schema": "public",
      "table": "accounts",
      "entityType": "columns"
    },
    {
      "type": "text",
      "typeSchema": null,
      "notNull": false,
      "dimensions": 0,
      "default": null,
      "generated": null,
      "identity": null,
      "name": "url",
      "schema": "public",
      "table": "accounts",
      "entityType": "columns"
    },
    {
      "type": "boolean",
      "typeSchema": null,
      "notNull": true,
      "dimensions": 0,
      "default": "false",
      "generated": null,
      "identity": null,
      "name": "protected",
      "schema": "public",
      "table": "accounts",
      "entityType": "columns"
    },
    {
      "type": "text",
      "typeSchema": null,
      "notNull": false,
      "dimensions": 0,
      "default": null,
      "generated": null,
      "identity": null,
      "name": "avatar_url",
      "schema": "public",
      "table": "accounts",
      "entityType": "columns"
    },
    {
      "type": "text",
      "typeSchema": null,
      "notNull": false,
      "dimensions": 0,
      "default": null,
      "generated": null,
      "identity": null,
      "name": "cover_url",
      "schema": "public",
      "table": "accounts",
      "entityType": "columns"
    },
    {
      "type": "text",
      "typeSchema": null,
      "notNull": true,
      "dimensions": 0,
      "default": null,
      "generated": null,
      "identity": null,
      "name": "inbox_url",
      "schema": "public",
      "table": "accounts",
      "entityType": "columns"
    },
    {
      "type": "text",
      "typeSchema": null,
      "notNull": false,
      "dimensions": 0,
      "default": null,
      "generated": null,
      "identity": null,
      "name": "followers_url",
      "schema": "public",
      "table": "accounts",
      "entityType": "columns"
    },
    {
      "type": "text",
      "typeSchema": null,
      "notNull": false,
      "dimensions": 0,
      "default": null,
      "generated": null,
      "identity": null,
      "name": "shared_inbox_url",
      "schema": "public",
      "table": "accounts",
      "entityType": "columns"
    },
    {
      "type": "text",
      "typeSchema": null,
      "notNull": false,
      "dimensions": 0,
      "default": null,
      "generated": null,
      "identity": null,
      "name": "featured_url",
      "schema": "public",
      "table": "accounts",
      "entityType": "columns"
    },
    {
      "type": "bigint",
      "typeSchema": null,
      "notNull": false,
      "dimensions": 0,
      "default": "0",
      "generated": null,
      "identity": null,
      "name": "following_count",
      "schema": "public",
      "table": "accounts",
      "entityType": "columns"
    },
    {
      "type": "bigint",
      "typeSchema": null,
      "notNull": false,
      "dimensions": 0,
      "default": "0",
      "generated": null,
      "identity": null,
      "name": "followers_count",
      "schema": "public",
      "table": "accounts",
      "entityType": "columns"
    },
    {
      "type": "bigint",
      "typeSchema": null,
      "notNull": false,
      "dimensions": 0,
      "default": "0",
      "generated": null,
      "identity": null,
      "name": "posts_count",
      "schema": "public",
      "table": "accounts",
      "entityType": "columns"
    },
    {
      "type": "json",
      "typeSchema": null,
      "notNull": true,
      "dimensions": 0,
      "default": "'{}'",
      "generated": null,
      "identity": null,
      "name": "field_htmls",
      "schema": "public",
      "table": "accounts",
      "entityType": "columns"
    },
    {
      "type": "jsonb",
      "typeSchema": null,
      "notNull": true,
      "dimensions": 0,
      "default": "'{}'",
      "generated": null,
      "identity": null,
      "name": "emojis",
      "schema": "public",
      "table": "accounts",
      "entityType": "columns"
    },
    {
      "type": "boolean",
      "typeSchema": null,
      "notNull": true,
      "dimensions": 0,
      "default": "false",
      "generated": null,
      "identity": null,
      "name": "sensitive",
      "schema": "public",
      "table": "accounts",
      "entityType": "columns"
    },
    {
      "type": "timestamp with time zone",
      "typeSchema": null,
      "notNull": false,
      "dimensions": 0,
      "default": null,
      "generated": null,
      "identity": null,
      "name": "published",
      "schema": "public",
      "table": "accounts",
      "entityType": "columns"
    },
    {
      "type": "timestamp with time zone",
      "typeSchema": null,
      "notNull": true,
      "dimensions": 0,
      "default": "now()",
      "generated": null,
      "identity": null,
      "name": "updated",
      "schema": "public",
      "table": "accounts",
      "entityType": "columns"
    },
    {
      "nameExplicit": false,
      "columns": [
        "iri"
      ],
      "nullsNotDistinct": false,
      "name": "accounts_iri_unique",
      "schema": "public",
      "table": "accounts",
      "entityType": "uniques"
    },
    {
      "nameExplicit": false,
      "columns": [
        "handle"
      ],
      "nullsNotDistinct": false,
      "name": "accounts_handle_unique",
      "schema": "public",
      "table": "accounts",
      "entityType": "uniques"
    },
    {
      "isRlsEnabled": false,
      "name": "applications",
      "schema": "public",
      "entityType": "tables"
    },
    {
      "columns": [
        "id"
      ],
      "nameExplicit": false,
      "name": "applications_pkey",
      "schema": "public",
      "table": "applications",
      "entityType": "pks"
    },
    {
      "type": "uuid",
      "typeSchema": null,
      "notNull": true,
      "dimensions": 0,
      "default": null,
      "generated": null,
      "identity": null,
      "name": "id",
      "schema": "public",
      "table": "applications",
      "entityType": "columns"
    },
    {
      "type": "varchar(256)",
      "typeSchema": null,
      "notNull": true,
      "dimensions": 0,
      "default": null,
      "generated": null,
      "identity": null,
      "name": "name",
      "schema": "public",
      "table": "applications",
      "entityType": "columns"
    },
    {
      "type": "text",
      "typeSchema": null,
      "notNull": true,
      "dimensions": 1,
      "default": null,
      "generated": null,
      "identity": null,
      "name": "redirect_uris",
      "schema": "public",
      "table": "applications",
      "entityType": "columns"
    },
    {
      "type": "scope",
      "typeSchema": null,
      "notNull": true,
      "dimensions": 1,
      "default": null,
      "generated": null,
      "identity": null,
      "name": "scopes",
      "schema": "public",
      "table": "applications",
      "entityType": "columns"
    },
    {
      "type": "text",
      "typeSchema": null,
      "notNull": false,
      "dimensions": 0,
      "default": null,
      "generated": null,
      "identity": null,
      "name": "website",
      "schema": "public",
      "table": "applications",
      "entityType": "columns"
    },
    {
      "type": "text",
      "typeSchema": null,
      "notNull": true,
      "dimensions": 0,
      "default": null,
      "generated": null,
      "identity": null,
      "name": "client_id",
      "schema": "public",
      "table": "applications",
      "entityType": "columns"
    },
    {
      "type": "text",
      "typeSchema": null,
      "notNull": true,
      "dimensions": 0,
      "default": null,
      "generated": null,
      "identity": null,
      "name": "client_secret",
      "schema": "public",
      "table": "applications",
      "entityType": "columns"
    },
    {
      "type": "timestamp with time zone",
      "typeSchema": null,
      "notNull": true,
      "dimensions": 0,
      "default": "now()",
      "generated": null,
      "identity": null,
      "name": "created",
      "schema": "public",
      "table": "applications",
      "entityType": "columns"
    },
    {
      "nameExplicit": false,
      "columns": [
        "client_id"
      ],
      "nullsNotDistinct": false,
      "name": "applications_client_id_unique",
      "schema": "public",
      "table": "applications",
      "entityType": "uniques"
    },
    {
      "isRlsEnabled": false,
      "name": "bookmarks",
      "schema": "public",
      "entityType": "tables"
    },
    {
      "type": "uuid",
      "typeSchema": null,
      "notNull": true,
      "dimensions": 0,
      "default": null,
      "generated": null,
      "identity": null,
      "name": "post_id",
      "schema": "public",
      "table": "bookmarks",
      "entityType": "columns"
    },
    {
      "type": "uuid",
      "typeSchema": null,
      "notNull": true,
      "dimensions": 0,
      "default": null,
      "generated": null,
      "identity": null,
      "name": "account_owner_id",
      "schema": "public",
      "table": "bookmarks",
      "entityType": "columns"
    },
    {
      "type": "timestamp with time zone",
      "typeSchema": null,
      "notNull": true,
      "dimensions": 0,
      "default": "now()",
      "generated": null,
      "identity": null,
      "name": "created",
      "schema": "public",
      "table": "bookmarks",
      "entityType": "columns"
    },
    {
      "columns": [
        "post_id",
        "account_owner_id"
      ],
      "nameExplicit": false,
      "name": "bookmarks_post_id_account_owner_id_pk",
      "schema": "public",
      "table": "bookmarks",
      "entityType": "pks"
    },
    {
      "nameExplicit": false,
      "columns": [
        {
          "value": "post_id",
          "isExpression": false,
          "asc": true,
          "nullsFirst": false,
          "opclass": null
        },
        {
          "value": "account_owner_id",
          "isExpression": false,
          "asc": true,
          "nullsFirst": false,
          "opclass": null
        }
      ],
      "isUnique": false,
      "where": null,
      "with": "",
      "method": "btree",
      "concurrently": false,
      "name": "bookmarks_post_id_account_owner_id_index",
      "schema": "public",
      "table": "bookmarks",
      "entityType": "indexes"
    },
    {
      "nameExplicit": false,
      "columns": [
        "post_id"
      ],
      "schemaTo": "public",
      "tableTo": "posts",
      "columnsTo": [
        "id"
      ],
      "onUpdate": "NO ACTION",
      "onDelete": "CASCADE",
      "name": "bookmarks_post_id_posts_id_fk",
      "schema": "public",
      "table": "bookmarks",
      "entityType": "fks"
    },
    {
      "nameExplicit": false,
      "columns": [
        "account_owner_id"
      ],
      "schemaTo": "public",
      "tableTo": "account_owners",
      "columnsTo": [
        "id"
      ],
      "onUpdate": "NO ACTION",
      "onDelete": "CASCADE",
      "name": "bookmarks_account_owner_id_account_owners_id_fk",
      "schema": "public",
      "table": "bookmarks",
      "entityType": "fks"
    },
    {
      "isRlsEnabled": false,
      "name": "credentials",
      "schema": "public",
      "entityType": "tables"
    },
    {
      "columns": [
        "email"
      ],
      "nameExplicit": false,
      "name": "credentials_pkey",
      "schema": "public",
      "table": "credentials",
      "entityType": "pks"
    },
    {
      "type": "varchar(254)",
      "typeSchema": null,
      "notNull": true,
      "dimensions": 0,
      "default": null,
      "generated": null,
      "identity": null,
      "name": "email",
      "schema": "public",
      "table": "credentials",
      "entityType": "columns"
    },
    {
      "type": "text",
      "typeSchema": null,
      "notNull": true,
      "dimensions": 0,
      "default": null,
      "generated": null,
      "identity": null,
      "name": "password_hash",
      "schema": "public",
      "table": "credentials",
      "entityType": "columns"
    },
    {
      "type": "timestamp with time zone",
      "typeSchema": null,
      "notNull": true,
      "dimensions": 0,
      "default": "now()",
      "generated": null,
      "identity": null,
      "name": "created",
      "schema": "public",
      "table": "credentials",
      "entityType": "columns"
    },
    {
      "isRlsEnabled": false,
      "name": "featured_tags",
      "schema": "public",
      "entityType": "tables"
    },
    {
      "columns": [
        "id"
      ],
      "nameExplicit": false,
      "name": "featured_tags_pkey",
      "schema": "public",
      "table": "featured_tags",
      "entityType": "pks"
    },
    {
      "type": "uuid",
      "typeSchema": null,
      "notNull": true,
      "dimensions": 0,
      "default": null,
      "generated": null,
      "identity": null,
      "name": "id",
      "schema": "public",
      "table": "featured_tags",
      "entityType": "columns"
    },
    {
      "type": "uuid",
      "typeSchema": null,
      "notNull": true,
      "dimensions": 0,
      "default": null,
      "generated": null,
      "identity": null,
      "name": "account_owner_id",
      "schema": "public",
      "table": "featured_tags",
      "entityType": "columns"
    },
    {
      "type": "text",
      "typeSchema": null,
      "notNull": true,
      "dimensions": 0,
      "default": null,
      "generated": null,
      "identity": null,
      "name": "name",
      "schema": "public",
      "table": "featured_tags",
      "entityType": "columns"
    },
    {
      "type": "timestamp with time zone",
      "typeSchema": null,
      "notNull": false,
      "dimensions": 0,
      "default": null,
      "generated": null,
      "identity": null,
      "name": "created",
      "schema": "public",
      "table": "featured_tags",
      "entityType": "columns"
    },
    {
      "nameExplicit": false,
      "columns": [
        "account_owner_id",
        "name"
      ],
      "nullsNotDistinct": false,
      "name": "featured_tags_account_owner_id_name_unique",
      "schema": "public",
      "table": "featured_tags",
      "entityType": "uniques"
    },
    {
      "nameExplicit": false,
      "columns": [
        "account_owner_id"
      ],
      "schemaTo": "public",
      "tableTo": "account_owners",
      "columnsTo": [
        "id"
      ],
      "onUpdate": "NO ACTION",
      "onDelete": "CASCADE",
      "name": "featured_tags_account_owner_id_account_owners_id_fk",
      "schema": "public",
      "table": "featured_tags",
      "entityType": "fks"
    },
    {
      "isRlsEnabled": false,
      "name": "follows",
      "schema": "public",
      "entityType": "tables"
    },
    {
      "type": "text",
      "typeSchema": null,
      "notNull": true,
      "dimensions": 0,
      "default": null,
      "generated": null,
      "identity": null,
      "name": "iri",
      "schema": "public",
      "table": "follows",
      "entityType": "columns"
    },
    {
      "type": "uuid",
      "typeSchema": null,
      "notNull": true,
      "dimensions": 0,
      "default": null,
      "generated": null,
      "identity": null,
      "name": "following_id",
      "schema": "public",
      "table": "follows",
      "entityType": "columns"
    },
    {
      "type": "uuid",
      "typeSchema": null,
      "notNull": true,
      "dimensions": 0,
      "default": null,
      "generated": null,
      "identity": null,
      "name": "follower_id",
      "schema": "public",
      "table": "follows",
      "entityType": "columns"
    },
    {
      "type": "boolean",
      "typeSchema": null,
      "notNull": true,
      "dimensions": 0,
      "default": "true",
      "generated": null,
      "identity": null,
      "name": "shares",
      "schema": "public",
      "table": "follows",
      "entityType": "columns"
    },
    {
      "type": "boolean",
      "typeSchema": null,
      "notNull": true,
      "dimensions": 0,
      "default": "false",
      "generated": null,
      "identity": null,
      "name": "notify",
      "schema": "public",
      "table": "follows",
      "entityType": "columns"
    },
    {
      "type": "text",
      "typeSchema": null,
      "notNull": false,
      "dimensions": 1,
      "default": null,
      "generated": null,
      "identity": null,
      "name": "languages",
      "schema": "public",
      "table": "follows",
      "entityType": "columns"
    },
    {
      "type": "timestamp with time zone",
      "typeSchema": null,
      "notNull": true,
      "dimensions": 0,
      "default": "now()",
      "generated": null,
      "identity": null,
      "name": "created",
      "schema": "public",
      "table": "follows",
      "entityType": "columns"
    },
    {
      "type": "timestamp with time zone",
      "typeSchema": null,
      "notNull": false,
      "dimensions": 0,
      "default": null,
      "generated": null,
      "identity": null,
      "name": "approved",
      "schema": "public",
      "table": "follows",
      "entityType": "columns"
    },
    {
      "columns": [
        "following_id",
        "follower_id"
      ],
      "nameExplicit": false,
      "name": "follows_following_id_follower_id_pk",
      "schema": "public",
      "table": "follows",
      "entityType": "pks"
    },
    {
      "nameExplicit": false,
      "columns": [
        "iri"
      ],
      "nullsNotDistinct": false,
      "name": "follows_iri_unique",
      "schema": "public",
      "table": "follows",
      "entityType": "uniques"
    },
    {
      "nameExplicit": false,
      "columns": [
        "following_id"
      ],
      "schemaTo": "public",
      "tableTo": "accounts",
      "columnsTo": [
        "id"
      ],
      "onUpdate": "NO ACTION",
      "onDelete": "CASCADE",
      "name": "follows_following_id_accounts_id_fk",
      "schema": "public",
      "table": "follows",
      "entityType": "fks"
    },
    {
      "nameExplicit": false,
      "columns": [
        "follower_id"
      ],
      "schemaTo": "public",
      "tableTo": "accounts",
      "columnsTo": [
        "id"
      ],
      "onUpdate": "NO ACTION",
      "onDelete": "CASCADE",
      "name": "follows_follower_id_accounts_id_fk",
      "schema": "public",
      "table": "follows",
      "entityType": "fks"
    },
    {
      "isRlsEnabled": false,
      "name": "likes",
      "schema": "public",
      "entityType": "tables"
    },
    {
      "type": "uuid",
      "typeSchema": null,
      "notNull": true,
      "dimensions": 0,
      "default": null,
      "generated": null,
      "identity": null,
      "name": "post_id",
      "schema": "public",
      "table": "likes",
      "entityType": "columns"
    },
    {
      "type": "uuid",
      "typeSchema": null,
      "notNull": true,
      "dimensions": 0,
      "default": null,
      "generated": null,
      "identity": null,
      "name": "account_id",
      "schema": "public",
      "table": "likes",
      "entityType": "columns"
    },
    {
      "type": "timestamp with time zone",
      "typeSchema": null,
      "notNull": true,
      "dimensions": 0,
      "default": "now()",
      "generated": null,
      "identity": null,
      "name": "created",
      "schema": "public",
      "table": "likes",
      "entityType": "columns"
    },
    {
      "columns": [
        "post_id",
        "account_id"
      ],
      "nameExplicit": false,
      "name": "likes_post_id_account_id_pk",
      "schema": "public",
      "table": "likes",
      "entityType": "pks"
    },
    {
      "nameExplicit": false,
      "columns": [
        "post_id"
      ],
      "schemaTo": "public",
      "tableTo": "posts",
      "columnsTo": [
        "id"
      ],
      "onUpdate": "NO ACTION",
      "onDelete": "CASCADE",
      "name": "likes_post_id_posts_id_fk",
      "schema": "public",
      "table": "likes",
      "entityType": "fks"
    },
    {
      "nameExplicit": false,
      "columns": [
        "account_id"
      ],
      "schemaTo": "public",
      "tableTo": "accounts",
      "columnsTo": [
        "id"
      ],
      "onUpdate": "NO ACTION",
      "onDelete": "CASCADE",
      "name": "likes_account_id_accounts_id_fk",
      "schema": "public",
      "table": "likes",
      "entityType": "fks"
    },
    {
      "isRlsEnabled": false,
      "name": "list_members",
      "schema": "public",
      "entityType": "tables"
    },
    {
      "type": "uuid",
      "typeSchema": null,
      "notNull": true,
      "dimensions": 0,
      "default": null,
      "generated": null,
      "identity": null,
      "name": "list_id",
      "schema": "public",
      "table": "list_members",
      "entityType": "columns"
    },
    {
      "type": "uuid",
      "typeSchema": null,
      "notNull": true,
      "dimensions": 0,
      "default": null,
      "generated": null,
      "identity": null,
      "name": "account_id",
      "schema": "public",
      "table": "list_members",
      "entityType": "columns"
    },
    {
      "type": "timestamp with time zone",
      "typeSchema": null,
      "notNull": true,
      "dimensions": 0,
      "default": "now()",
      "generated": null,
      "identity": null,
      "name": "created",
      "schema": "public",
      "table": "list_members",
      "entityType": "columns"
    },
    {
      "columns": [
        "list_id",
        "account_id"
      ],
      "nameExplicit": false,
      "name": "list_members_list_id_account_id_pk",
      "schema": "public",
      "table": "list_members",
      "entityType": "pks"
    },
    {
      "nameExplicit": false,
      "columns": [
        "list_id"
      ],
      "schemaTo": "public",
      "tableTo": "lists",
      "columnsTo": [
        "id"
      ],
      "onUpdate": "NO ACTION",
      "onDelete": "CASCADE",
      "name": "list_members_list_id_lists_id_fk",
      "schema": "public",
      "table": "list_members",
      "entityType": "fks"
    },
    {
      "nameExplicit": false,
      "columns": [
        "account_id"
      ],
      "schemaTo": "public",
      "tableTo": "accounts",
      "columnsTo": [
        "id"
      ],
      "onUpdate": "NO ACTION",
      "onDelete": "CASCADE",
      "name": "list_members_account_id_accounts_id_fk",
      "schema": "public",
      "table": "list_members",
      "entityType": "fks"
    },
    {
      "isRlsEnabled": false,
      "name": "lists",
      "schema": "public",
      "entityType": "tables"
    },
    {
      "columns": [
        "id"
      ],
      "nameExplicit": false,
      "name": "lists_pkey",
      "schema": "public",
      "table": "lists",
      "entityType": "pks"
    },
    {
      "type": "uuid",
      "typeSchema": null,
      "notNull": true,
      "dimensions": 0,
      "default": null,
      "generated": null,
      "identity": null,
      "name": "id",
      "schema": "public",
      "table": "lists",
      "entityType": "columns"
    },
    {
      "type": "uuid",
      "typeSchema": null,
      "notNull": true,
      "dimensions": 0,
      "default": null,
      "generated": null,
      "identity": null,
      "name": "account_owner_id",
      "schema": "public",
      "table": "lists",
      "entityType": "columns"
    },
    {
      "type": "text",
      "typeSchema": null,
      "notNull": true,
      "dimensions": 0,
      "default": null,
      "generated": null,
      "identity": null,
      "name": "title",
      "schema": "public",
      "table": "lists",
      "entityType": "columns"
    },
    {
      "type": "list_replies_policy",
      "typeSchema": "public",
      "notNull": true,
      "dimensions": 0,
      "default": "'list'",
      "generated": null,
      "identity": null,
      "name": "replies_policy",
      "schema": "public",
      "table": "lists",
      "entityType": "columns"
    },
    {
      "type": "boolean",
      "typeSchema": null,
      "notNull": true,
      "dimensions": 0,
      "default": "false",
      "generated": null,
      "identity": null,
      "name": "exclusive",
      "schema": "public",
      "table": "lists",
      "entityType": "columns"
    },
    {
      "type": "timestamp with time zone",
      "typeSchema": null,
      "notNull": true,
      "dimensions": 0,
      "default": "now()",
      "generated": null,
      "identity": null,
      "name": "created",
      "schema": "public",
      "table": "lists",
      "entityType": "columns"
    },
    {
      "nameExplicit": false,
      "columns": [
        "account_owner_id"
      ],
      "schemaTo": "public",
      "tableTo": "account_owners",
      "columnsTo": [
        "id"
      ],
      "onUpdate": "NO ACTION",
      "onDelete": "CASCADE",
      "name": "lists_account_owner_id_account_owners_id_fk",
      "schema": "public",
      "table": "lists",
      "entityType": "fks"
    },
    {
      "isRlsEnabled": false,
      "name": "markers",
      "schema": "public",
      "entityType": "tables"
    },
    {
      "type": "uuid",
      "typeSchema": null,
      "notNull": true,
      "dimensions": 0,
      "default": null,
      "generated": null,
      "identity": null,
      "name": "account_owner_id",
      "schema": "public",
      "table": "markers",
      "entityType": "columns"
    },
    {
      "type": "marker_type",
      "typeSchema": "public",
      "notNull": true,
      "dimensions": 0,
      "default": null,
      "generated": null,
      "identity": null,
      "name": "type",
      "schema": "public",
      "table": "markers",
      "entityType": "columns"
    },
    {
      "type": "text",
      "typeSchema": null,
      "notNull": true,
      "dimensions": 0,
      "default": null,
      "generated": null,
      "identity": null,
      "name": "last_read_id",
      "schema": "public",
      "table": "markers",
      "entityType": "columns"
    },
    {
      "type": "bigint",
      "typeSchema": null,
      "notNull": true,
      "dimensions": 0,
      "default": "1",
      "generated": null,
      "identity": null,
      "name": "version",
      "schema": "public",
      "table": "markers",
      "entityType": "columns"
    },
    {
      "type": "timestamp with time zone",
      "typeSchema": null,
      "notNull": true,
      "dimensions": 0,
      "default": "now()",
      "generated": null,
      "identity": null,
      "name": "updated",
      "schema": "public",
      "table": "markers",
      "entityType": "columns"
    },
    {
      "columns": [
        "account_owner_id",
        "type"
      ],
      "nameExplicit": false,
      "name": "markers_account_owner_id_type_pk",
      "schema": "public",
      "table": "markers",
      "entityType": "pks"
    },
    {
      "nameExplicit": false,
      "columns": [
        "account_owner_id"
      ],
      "schemaTo": "public",
      "tableTo": "account_owners",
      "columnsTo": [
        "id"
      ],
      "onUpdate": "NO ACTION",
      "onDelete": "CASCADE",
      "name": "markers_account_owner_id_account_owners_id_fk",
      "schema": "public",
      "table": "markers",
      "entityType": "fks"
    },
    {
      "isRlsEnabled": false,
      "name": "media",
      "schema": "public",
      "entityType": "tables"
    },
    {
      "columns": [
        "id"
      ],
      "nameExplicit": false,
      "name": "media_pkey",
      "schema": "public",
      "table": "media",
      "entityType": "pks"
    },
    {
      "type": "uuid",
      "typeSchema": null,
      "notNull": true,
      "dimensions": 0,
      "default": null,
      "generated": null,
      "identity": null,
      "name": "id",
      "schema": "public",
      "table": "media",
      "entityType": "columns"
    },
    {
      "type": "uuid",
      "typeSchema": null,
      "notNull": false,
      "dimensions": 0,
      "default": null,
      "generated": null,
      "identity": null,
      "name": "post_id",
      "schema": "public",
      "table": "media",
      "entityType": "columns"
    },
    {
      "type": "text",
      "typeSchema": null,
      "notNull": true,
      "dimensions": 0,
      "default": null,
      "generated": null,
      "identity": null,
      "name": "type",
      "schema": "public",
      "table": "media",
      "entityType": "columns"
    },
    {
      "type": "text",
      "typeSchema": null,
      "notNull": true,
      "dimensions": 0,
      "default": null,
      "generated": null,
      "identity": null,
      "name": "url",
      "schema": "public",
      "table": "media",
      "entityType": "columns"
    },
    {
      "type": "integer",
      "typeSchema": null,
      "notNull": true,
      "dimensions": 0,
      "default": null,
      "generated": null,
      "identity": null,
      "name": "width",
      "schema": "public",
      "table": "media",
      "entityType": "columns"
    },
    {
      "type": "integer",
      "typeSchema": null,
      "notNull": true,
      "dimensions": 0,
      "default": null,
      "generated": null,
      "identity": null,
      "name": "height",
      "schema": "public",
      "table": "media",
      "entityType": "columns"
    },
    {
      "type": "text",
      "typeSchema": null,
      "notNull": false,
      "dimensions": 0,
      "default": null,
      "generated": null,
      "identity": null,
      "name": "description",
      "schema": "public",
      "table": "media",
      "entityType": "columns"
    },
    {
      "type": "text",
      "typeSchema": null,
      "notNull": true,
      "dimensions": 0,
      "default": null,
      "generated": null,
      "identity": null,
      "name": "thumbnail_type",
      "schema": "public",
      "table": "media",
      "entityType": "columns"
    },
    {
      "type": "text",
      "typeSchema": null,
      "notNull": true,
      "dimensions": 0,
      "default": null,
      "generated": null,
      "identity": null,
      "name": "thumbnail_url",
      "schema": "public",
      "table": "media",
      "entityType": "columns"
    },
    {
      "type": "integer",
      "typeSchema": null,
      "notNull": true,
      "dimensions": 0,
      "default": null,
      "generated": null,
      "identity": null,
      "name": "thumbnail_width",
      "schema": "public",
      "table": "media",
      "entityType": "columns"
    },
    {
      "type": "integer",
      "typeSchema": null,
      "notNull": true,
      "dimensions": 0,
      "default": null,
      "generated": null,
      "identity": null,
      "name": "thumbnail_height",
      "schema": "public",
      "table": "media",
      "entityType": "columns"
    },
    {
      "type": "timestamp with time zone",
      "typeSchema": null,
      "notNull": true,
      "dimensions": 0,
      "default": "now()",
      "generated": null,
      "identity": null,
      "name": "created",
      "schema": "public",
      "table": "media",
      "entityType": "columns"
    },
    {
      "nameExplicit": false,
      "columns": [
        {
          "value": "post_id",
          "isExpression": false,
          "asc": true,
          "nullsFirst": false,
          "opclass": null
        }
      ],
      "isUnique": false,
      "where": null,
      "with": "",
      "method": "btree",
      "concurrently": false,
      "name": "media_post_id_index",
      "schema": "public",
      "table": "media",
      "entityType": "indexes"
    },
    {
      "nameExplicit": false,
      "columns": [
        "post_id"
      ],
      "schemaTo": "public",
      "tableTo": "posts",
      "columnsTo": [
        "id"
      ],
      "onUpdate": "NO ACTION",
      "onDelete": "CASCADE",
      "name": "media_post_id_posts_id_fk",
      "schema": "public",
      "table": "media",
      "entityType": "fks"
    },
    {
      "isRlsEnabled": false,
      "name": "mentions",
      "schema": "public",
      "entityType": "tables"
    },
    {
      "type": "uuid",
      "typeSchema": null,
      "notNull": true,
      "dimensions": 0,
      "default": null,
      "generated": null,
      "identity": null,
      "name": "post_id",
      "schema": "public",
      "table": "mentions",
      "entityType": "columns"
    },
    {
      "type": "uuid",
      "typeSchema": null,
      "notNull": true,
      "dimensions": 0,
      "default": null,
      "generated": null,
      "identity": null,
      "name": "account_id",
      "schema": "public",
      "table": "mentions",
      "entityType": "columns"
    },
    {
      "columns": [
        "post_id",
        "account_id"
      ],
      "nameExplicit": false,
      "name": "mentions_post_id_account_id_pk",
      "schema": "public",
      "table": "mentions",
      "entityType": "pks"
    },
    {
      "nameExplicit": false,
      "columns": [
        "post_id"
      ],
      "schemaTo": "public",
      "tableTo": "posts",
      "columnsTo": [
        "id"
      ],
      "onUpdate": "NO ACTION",
      "onDelete": "CASCADE",
      "name": "mentions_post_id_posts_id_fk",
      "schema": "public",
      "table": "mentions",
      "entityType": "fks"
    },
    {
      "nameExplicit": false,
      "columns": [
        "account_id"
      ],
      "schemaTo": "public",
      "tableTo": "accounts",
      "columnsTo": [
        "id"
      ],
      "onUpdate": "NO ACTION",
      "onDelete": "CASCADE",
      "name": "mentions_account_id_accounts_id_fk",
      "schema": "public",
      "table": "mentions",
      "entityType": "fks"
    },
    {
      "isRlsEnabled": false,
      "name": "mutes",
      "schema": "public",
      "entityType": "tables"
    },
    {
      "columns": [
        "id"
      ],
      "nameExplicit": false,
      "name": "mutes_pkey",
      "schema": "public",
      "table": "mutes",
      "entityType": "pks"
    },
    {
      "type": "uuid",
      "typeSchema": null,
      "notNull": true,
      "dimensions": 0,
      "default": null,
      "generated": null,
      "identity": null,
      "name": "id",
      "schema": "public",
      "table": "mutes",
      "entityType": "columns"
    },
    {
      "type": "uuid",
      "typeSchema": null,
      "notNull": true,
      "dimensions": 0,
      "default": null,
      "generated": null,
      "identity": null,
      "name": "account_id",
      "schema": "public",
      "table": "mutes",
      "entityType": "columns"
    },
    {
      "type": "uuid",
      "typeSchema": null,
      "notNull": true,
      "dimensions": 0,
      "default": null,
      "generated": null,
      "identity": null,
      "name": "muted_account_id",
      "schema": "public",
      "table": "mutes",
      "entityType": "columns"
    },
    {
      "type": "boolean",
      "typeSchema": null,
      "notNull": true,
      "dimensions": 0,
      "default": "true",
      "generated": null,
      "identity": null,
      "name": "notifications",
      "schema": "public",
      "table": "mutes",
      "entityType": "columns"
    },
    {
      "type": "integer",
      "typeSchema": null,
      "notNull": true,
      "dimensions": 0,
      "default": "0",
      "generated": null,
      "identity": null,
      "name": "duration",
      "schema": "public",
      "table": "mutes",
      "entityType": "columns"
    },
    {
      "type": "timestamp with time zone",
      "typeSchema": null,
      "notNull": true,
      "dimensions": 0,
      "default": "now()",
      "generated": null,
      "identity": null,
      "name": "created",
      "schema": "public",
      "table": "mutes",
      "entityType": "columns"
    },
    {
      "nameExplicit": false,
      "columns": [
        "account_id",
        "muted_account_id"
      ],
      "nullsNotDistinct": false,
      "name": "mutes_account_id_muted_account_id_unique",
      "schema": "public",
      "table": "mutes",
      "entityType": "uniques"
    },
    {
      "nameExplicit": false,
      "columns": [
        "account_id"
      ],
      "schemaTo": "public",
      "tableTo": "accounts",
      "columnsTo": [
        "id"
      ],
      "onUpdate": "NO ACTION",
      "onDelete": "CASCADE",
      "name": "mutes_account_id_accounts_id_fk",
      "schema": "public",
      "table": "mutes",
      "entityType": "fks"
    },
    {
      "nameExplicit": false,
      "columns": [
        "muted_account_id"
      ],
      "schemaTo": "public",
      "tableTo": "accounts",
      "columnsTo": [
        "id"
      ],
      "onUpdate": "NO ACTION",
      "onDelete": "CASCADE",
      "name": "mutes_muted_account_id_accounts_id_fk",
      "schema": "public",
      "table": "mutes",
      "entityType": "fks"
    },
    {
      "isRlsEnabled": false,
      "name": "pinned_posts",
      "schema": "public",
      "entityType": "tables"
    },
    {
      "columns": [
        "index"
      ],
      "nameExplicit": false,
      "name": "pinned_posts_pkey",
      "schema": "public",
      "table": "pinned_posts",
      "entityType": "pks"
    },
    {
      "type": "bigserial",
      "typeSchema": null,
      "notNull": true,
      "dimensions": 0,
      "default": null,
      "generated": null,
      "identity": null,
      "name": "index",
      "schema": "public",
      "table": "pinned_posts",
      "entityType": "columns"
    },
    {
      "type": "uuid",
      "typeSchema": null,
      "notNull": true,
      "dimensions": 0,
      "default": null,
      "generated": null,
      "identity": null,
      "name": "post_id",
      "schema": "public",
      "table": "pinned_posts",
      "entityType": "columns"
    },
    {
      "type": "uuid",
      "typeSchema": null,
      "notNull": true,
      "dimensions": 0,
      "default": null,
      "generated": null,
      "identity": null,
      "name": "account_id",
      "schema": "public",
      "table": "pinned_posts",
      "entityType": "columns"
    },
    {
      "type": "timestamp with time zone",
      "typeSchema": null,
      "notNull": true,
      "dimensions": 0,
      "default": "now()",
      "generated": null,
      "identity": null,
      "name": "created",
      "schema": "public",
      "table": "pinned_posts",
      "entityType": "columns"
    },
    {
      "nameExplicit": false,
      "columns": [
        "post_id",
        "account_id"
      ],
      "nullsNotDistinct": false,
      "name": "pinned_posts_post_id_account_id_unique",
      "schema": "public",
      "table": "pinned_posts",
      "entityType": "uniques"
    },
    {
      "nameExplicit": false,
      "columns": [
        "account_id"
      ],
      "schemaTo": "public",
      "tableTo": "accounts",
      "columnsTo": [
        "id"
      ],
      "onUpdate": "NO ACTION",
      "onDelete": "CASCADE",
      "name": "pinned_posts_account_id_accounts_id_fk",
      "schema": "public",
      "table": "pinned_posts",
      "entityType": "fks"
    },
    {
      "nameExplicit": false,
      "columns": [
        "post_id",
        "account_id"
      ],
      "schemaTo": "public",
      "tableTo": "posts",
      "columnsTo": [
        "id",
        "actor_id"
      ],
      "onUpdate": "NO ACTION",
      "onDelete": "CASCADE",
      "name": "pinned_posts_post_id_account_id_posts_id_actor_id_fk",
      "schema": "public",
      "table": "pinned_posts",
      "entityType": "fks"
    },
    {
      "isRlsEnabled": false,
      "name": "poll_options",
      "schema": "public",
      "entityType": "tables"
    },
    {
      "type": "uuid",
      "typeSchema": null,
      "notNull": false,
      "dimensions": 0,
      "default": null,
      "generated": null,
      "identity": null,
      "name": "poll_id",
      "schema": "public",
      "table": "poll_options",
      "entityType": "columns"
    },
    {
      "type": "integer",
      "typeSchema": null,
      "notNull": true,
      "dimensions": 0,
      "default": null,
      "generated": null,
      "identity": null,
      "name": "index",
      "schema": "public",
      "table": "poll_options",
      "entityType": "columns"
    },
    {
      "type": "text",
      "typeSchema": null,
      "notNull": true,
      "dimensions": 0,
      "default": null,
      "generated": null,
      "identity": null,
      "name": "title",
      "schema": "public",
      "table": "poll_options",
      "entityType": "columns"
    },
    {
      "type": "bigint",
      "typeSchema": null,
      "notNull": true,
      "dimensions": 0,
      "default": "0",
      "generated": null,
      "identity": null,
      "name": "votes_count",
      "schema": "public",
      "table": "poll_options",
      "entityType": "columns"
    },
    {
      "columns": [
        "poll_id",
        "index"
      ],
      "nameExplicit": false,
      "name": "poll_options_poll_id_index_pk",
      "schema": "public",
      "table": "poll_options",
      "entityType": "pks"
    },
    {
      "nameExplicit": false,
      "columns": [
        "poll_id",
        "title"
      ],
      "nullsNotDistinct": false,
      "name": "poll_options_poll_id_title_unique",
      "schema": "public",
      "table": "poll_options",
      "entityType": "uniques"
    },
    {
      "nameExplicit": false,
      "columns": [
        "poll_id"
      ],
      "schemaTo": "public",
      "tableTo": "polls",
      "columnsTo": [
        "id"
      ],
      "onUpdate": "NO ACTION",
      "onDelete": "CASCADE",
      "name": "poll_options_poll_id_polls_id_fk",
      "schema": "public",
      "table": "poll_options",
      "entityType": "fks"
    },
    {
      "isRlsEnabled": false,
      "name": "poll_votes",
      "schema": "public",
      "entityType": "tables"
    },
    {
      "type": "uuid",
      "typeSchema": null,
      "notNull": true,
      "dimensions": 0,
      "default": null,
      "generated": null,
      "identity": null,
      "name": "poll_id",
      "schema": "public",
      "table": "poll_votes",
      "entityType": "columns"
    },
    {
      "type": "integer",
      "typeSchema": null,
      "notNull": true,
      "dimensions": 0,
      "default": null,
      "generated": null,
      "identity": null,
      "name": "option_index",
      "schema": "public",
      "table": "poll_votes",
      "entityType": "columns"
    },
    {
      "type": "uuid",
      "typeSchema": null,
      "notNull": true,
      "dimensions": 0,
      "default": null,
      "generated": null,
      "identity": null,
      "name": "account_id",
      "schema": "public",
      "table": "poll_votes",
      "entityType": "columns"
    },
    {
      "type": "timestamp with time zone",
      "typeSchema": null,
      "notNull": true,
      "dimensions": 0,
      "default": "now()",
      "generated": null,
      "identity": null,
      "name": "created",
      "schema": "public",
      "table": "poll_votes",
      "entityType": "columns"
    },
    {
      "columns": [
        "poll_id",
        "option_index",
        "account_id"
      ],
      "nameExplicit": false,
      "name": "poll_votes_poll_id_option_index_account_id_pk",
      "schema": "public",
      "table": "poll_votes",
      "entityType": "pks"
    },
    {
      "nameExplicit": false,
      "columns": [
        {
          "value": "poll_id",
          "isExpression": false,
          "asc": true,
          "nullsFirst": false,
          "opclass": null
        },
        {
          "value": "account_id",
          "isExpression": false,
          "asc": true,
          "nullsFirst": false,
          "opclass": null
        }
      ],
      "isUnique": false,
      "where": null,
      "with": "",
      "method": "btree",
      "concurrently": false,
      "name": "poll_votes_poll_id_account_id_index",
      "schema": "public",
      "table": "poll_votes",
      "entityType": "indexes"
    },
    {
      "nameExplicit": false,
      "columns": [
        "poll_id"
      ],
      "schemaTo": "public",
      "tableTo": "polls",
      "columnsTo": [
        "id"
      ],
      "onUpdate": "NO ACTION",
      "onDelete": "CASCADE",
      "name": "poll_votes_poll_id_polls_id_fk",
      "schema": "public",
      "table": "poll_votes",
      "entityType": "fks"
    },
    {
      "nameExplicit": false,
      "columns": [
        "account_id"
      ],
      "schemaTo": "public",
      "tableTo": "accounts",
      "columnsTo": [
        "id"
      ],
      "onUpdate": "NO ACTION",
      "onDelete": "CASCADE",
      "name": "poll_votes_account_id_accounts_id_fk",
      "schema": "public",
      "table": "poll_votes",
      "entityType": "fks"
    },
    {
      "nameExplicit": false,
      "columns": [
        "poll_id",
        "option_index"
      ],
      "schemaTo": "public",
      "tableTo": "poll_options",
      "columnsTo": [
        "poll_id",
        "index"
      ],
      "onUpdate": "NO ACTION",
      "onDelete": "NO ACTION",
      "name": "poll_votes_poll_id_option_index_poll_options_poll_id_index_fk",
      "schema": "public",
      "table": "poll_votes",
      "entityType": "fks"
    },
    {
      "isRlsEnabled": false,
      "name": "polls",
      "schema": "public",
      "entityType": "tables"
    },
    {
      "columns": [
        "id"
      ],
      "nameExplicit": false,
      "name": "polls_pkey",
      "schema": "public",
      "table": "polls",
      "entityType": "pks"
    },
    {
      "type": "uuid",
      "typeSchema": null,
      "notNull": true,
      "dimensions": 0,
      "default": null,
      "generated": null,
      "identity": null,
      "name": "id",
      "schema": "public",
      "table": "polls",
      "entityType": "columns"
    },
    {
      "type": "boolean",
      "typeSchema": null,
      "notNull": true,
      "dimensions": 0,
      "default": "false",
      "generated": null,
      "identity": null,
      "name": "multiple",
      "schema": "public",
      "table": "polls",
      "entityType": "columns"
    },
    {
      "type": "bigint",
      "typeSchema": null,
      "notNull": true,
      "dimensions": 0,
      "default": "0",
      "generated": null,
      "identity": null,
      "name": "voters_count",
      "schema": "public",
      "table": "polls",
      "entityType": "columns"
    },
    {
      "type": "timestamp with time zone",
      "typeSchema": null,
      "notNull": true,
      "dimensions": 0,
      "default": null,
      "generated": null,
      "identity": null,
      "name": "expires",
      "schema": "public",
      "table": "polls",
      "entityType": "columns"
    },
    {
      "type": "timestamp with time zone",
      "typeSchema": null,
      "notNull": true,
      "dimensions": 0,
      "default": "now()",
      "generated": null,
      "identity": null,
      "name": "created",
      "schema": "public",
      "table": "polls",
      "entityType": "columns"
    },
    {
      "isRlsEnabled": false,
      "name": "posts",
      "schema": "public",
      "entityType": "tables"
    },
    {
      "columns": [
        "id"
      ],
      "nameExplicit": false,
      "name": "posts_pkey",
      "schema": "public",
      "table": "posts",
      "entityType": "pks"
    },
    {
      "type": "uuid",
      "typeSchema": null,
      "notNull": true,
      "dimensions": 0,
      "default": null,
      "generated": null,
      "identity": null,
      "name": "id",
      "schema": "public",
      "table": "posts",
      "entityType": "columns"
    },
    {
      "type": "text",
      "typeSchema": null,
      "notNull": true,
      "dimensions": 0,
      "default": null,
      "generated": null,
      "identity": null,
      "name": "iri",
      "schema": "public",
      "table": "posts",
      "entityType": "columns"
    },
    {
      "type": "post_type",
      "typeSchema": "public",
      "notNull": true,
      "dimensions": 0,
      "default": null,
      "generated": null,
      "identity": null,
      "name": "type",
      "schema": "public",
      "table": "posts",
      "entityType": "columns"
    },
    {
      "type": "uuid",
      "typeSchema": null,
      "notNull": true,
      "dimensions": 0,
      "default": null,
      "generated": null,
      "identity": null,
      "name": "actor_id",
      "schema": "public",
      "table": "posts",
      "entityType": "columns"
    },
    {
      "type": "uuid",
      "typeSchema": null,
      "notNull": false,
      "dimensions": 0,
      "default": null,
      "generated": null,
      "identity": null,
      "name": "application_id",
      "schema": "public",
      "table": "posts",
      "entityType": "columns"
    },
    {
      "type": "uuid",
      "typeSchema": null,
      "notNull": false,
      "dimensions": 0,
      "default": null,
      "generated": null,
      "identity": null,
      "name": "reply_target_id",
      "schema": "public",
      "table": "posts",
      "entityType": "columns"
    },
    {
      "type": "uuid",
      "typeSchema": null,
      "notNull": false,
      "dimensions": 0,
      "default": null,
      "generated": null,
      "identity": null,
      "name": "sharing_id",
      "schema": "public",
      "table": "posts",
      "entityType": "columns"
    },
    {
      "type": "uuid",
      "typeSchema": null,
      "notNull": false,
      "dimensions": 0,
      "default": null,
      "generated": null,
      "identity": null,
      "name": "quote_target_id",
      "schema": "public",
      "table": "posts",
      "entityType": "columns"
    },
    {
      "type": "post_visibility",
      "typeSchema": "public",
      "notNull": true,
      "dimensions": 0,
      "default": null,
      "generated": null,
      "identity": null,
      "name": "visibility",
      "schema": "public",
      "table": "posts",
      "entityType": "columns"
    },
    {
      "type": "text",
      "typeSchema": null,
      "notNull": false,
      "dimensions": 0,
      "default": null,
      "generated": null,
      "identity": null,
      "name": "summary_html",
      "schema": "public",
      "table": "posts",
      "entityType": "columns"
    },
    {
      "type": "text",
      "typeSchema": null,
      "notNull": false,
      "dimensions": 0,
      "default": null,
      "generated": null,
      "identity": null,
      "name": "summary",
      "schema": "public",
      "table": "posts",
      "entityType": "columns"
    },
    {
      "type": "text",
      "typeSchema": null,
      "notNull": false,
      "dimensions": 0,
      "default": null,
      "generated": null,
      "identity": null,
      "name": "content_html",
      "schema": "public",
      "table": "posts",
      "entityType": "columns"
    },
    {
      "type": "text",
      "typeSchema": null,
      "notNull": false,
      "dimensions": 0,
      "default": null,
      "generated": null,
      "identity": null,
      "name": "content",
      "schema": "public",
      "table": "posts",
      "entityType": "columns"
    },
    {
      "type": "uuid",
      "typeSchema": null,
      "notNull": false,
      "dimensions": 0,
      "default": null,
      "generated": null,
      "identity": null,
      "name": "poll_id",
      "schema": "public",
      "table": "posts",
      "entityType": "columns"
    },
    {
      "type": "text",
      "typeSchema": null,
      "notNull": false,
      "dimensions": 0,
      "default": null,
      "generated": null,
      "identity": null,
      "name": "language",
      "schema": "public",
      "table": "posts",
      "entityType": "columns"
    },
    {
      "type": "jsonb",
      "typeSchema": null,
      "notNull": true,
      "dimensions": 0,
      "default": "'{}'",
      "generated": null,
      "identity": null,
      "name": "tags",
      "schema": "public",
      "table": "posts",
      "entityType": "columns"
    },
    {
      "type": "jsonb",
      "typeSchema": null,
      "notNull": true,
      "dimensions": 0,
      "default": "'{}'",
      "generated": null,
      "identity": null,
      "name": "emojis",
      "schema": "public",
      "table": "posts",
      "entityType": "columns"
    },
    {
      "type": "boolean",
      "typeSchema": null,
      "notNull": true,
      "dimensions": 0,
      "default": "false",
      "generated": null,
      "identity": null,
      "name": "sensitive",
      "schema": "public",
      "table": "posts",
      "entityType": "columns"
    },
    {
      "type": "text",
      "typeSchema": null,
      "notNull": false,
      "dimensions": 0,
      "default": null,
      "generated": null,
      "identity": null,
      "name": "url",
      "schema": "public",
      "table": "posts",
      "entityType": "columns"
    },
    {
      "type": "jsonb",
      "typeSchema": null,
      "notNull": false,
      "dimensions": 0,
      "default": null,
      "generated": null,
      "identity": null,
      "name": "preview_card",
      "schema": "public",
      "table": "posts",
      "entityType": "columns"
    },
    {
      "type": "bigint",
      "typeSchema": null,
      "notNull": false,
      "dimensions": 0,
      "default": "0",
      "generated": null,
      "identity": null,
      "name": "replies_count",
      "schema": "public",
      "table": "posts",
      "entityType": "columns"
    },
    {
      "type": "bigint",
      "typeSchema": null,
      "notNull": false,
      "dimensions": 0,
      "default": "0",
      "generated": null,
      "identity": null,
      "name": "shares_count",
      "schema": "public",
      "table": "posts",
      "entityType": "columns"
    },
    {
      "type": "bigint",
      "typeSchema": null,
      "notNull": false,
      "dimensions": 0,
      "default": "0",
      "generated": null,
      "identity": null,
      "name": "likes_count",
      "schema": "public",
      "table": "posts",
      "entityType": "columns"
    },
    {
      "type": "timestamp with time zone",
      "typeSchema": null,
      "notNull": false,
      "dimensions": 0,
      "default": null,
      "generated": null,
      "identity": null,
      "name": "published",
      "schema": "public",
      "table": "posts",
      "entityType": "columns"
    },
    {
      "type": "timestamp with time zone",
      "typeSchema": null,
      "notNull": true,
      "dimensions": 0,
      "default": "now()",
      "generated": null,
      "identity": null,
      "name": "updated",
      "schema": "public",
      "table": "posts",
      "entityType": "columns"
    },
    {
      "nameExplicit": false,
      "columns": [
        "iri"
      ],
      "nullsNotDistinct": false,
      "name": "posts_iri_unique",
      "schema": "public",
      "table": "posts",
      "entityType": "uniques"
    },
    {
      "nameExplicit": false,
      "columns": [
        "id",
        "actor_id"
      ],
      "nullsNotDistinct": false,
      "name": "posts_id_actor_id_unique",
      "schema": "public",
      "table": "posts",
      "entityType": "uniques"
    },
    {
      "nameExplicit": false,
      "columns": [
        "poll_id"
      ],
      "nullsNotDistinct": false,
      "name": "posts_poll_id_unique",
      "schema": "public",
      "table": "posts",
      "entityType": "uniques"
    },
    {
      "nameExplicit": false,
      "columns": [
        {
          "value": "sharing_id",
          "isExpression": false,
          "asc": true,
          "nullsFirst": false,
          "opclass": null
        }
      ],
      "isUnique": false,
      "where": null,
      "with": "",
      "method": "btree",
      "concurrently": false,
      "name": "posts_sharing_id_index",
      "schema": "public",
      "table": "posts",
      "entityType": "indexes"
    },
    {
      "nameExplicit": false,
      "columns": [
        {
          "value": "actor_id",
          "isExpression": false,
          "asc": true,
          "nullsFirst": false,
          "opclass": null
        },
        {
          "value": "sharing_id",
          "isExpression": false,
          "asc": true,
          "nullsFirst": false,
          "opclass": null
        }
      ],
      "isUnique": false,
      "where": null,
      "with": "",
      "method": "btree",
      "concurrently": false,
      "name": "posts_actor_id_sharing_id_index",
      "schema": "public",
      "table": "posts",
      "entityType": "indexes"
    },
    {
      "nameExplicit": false,
      "columns": [
        {
          "value": "reply_target_id",
          "isExpression": false,
          "asc": true,
          "nullsFirst": false,
          "opclass": null
        }
      ],
      "isUnique": false,
      "where": null,
      "with": "",
      "method": "btree",
      "concurrently": false,
      "name": "posts_reply_target_id_index",
      "schema": "public",
      "table": "posts",
      "entityType": "indexes"
    },
    {
      "nameExplicit": false,
      "columns": [
        "actor_id"
      ],
      "schemaTo": "public",
      "tableTo": "accounts",
      "columnsTo": [
        "id"
      ],
      "onUpdate": "NO ACTION",
      "onDelete": "CASCADE",
      "name": "posts_actor_id_accounts_id_fk",
      "schema": "public",
      "table": "posts",
      "entityType": "fks"
    },
    {
      "nameExplicit": false,
      "columns": [
        "application_id"
      ],
      "schemaTo": "public",
      "tableTo": "applications",
      "columnsTo": [
        "id"
      ],
      "onUpdate": "NO ACTION",
      "onDelete": "SET NULL",
      "name": "posts_application_id_applications_id_fk",
      "schema": "public",
      "table": "posts",
      "entityType": "fks"
    },
    {
      "nameExplicit": false,
      "columns": [
        "reply_target_id"
      ],
      "schemaTo": "public",
      "tableTo": "posts",
      "columnsTo": [
        "id"
      ],
      "onUpdate": "NO ACTION",
      "onDelete": "SET NULL",
      "name": "posts_reply_target_id_posts_id_fk",
      "schema": "public",
      "table": "posts",
      "entityType": "fks"
    },
    {
      "nameExplicit": false,
      "columns": [
        "sharing_id"
      ],
      "schemaTo": "public",
      "tableTo": "posts",
      "columnsTo": [
        "id"
      ],
      "onUpdate": "NO ACTION",
      "onDelete": "CASCADE",
      "name": "posts_sharing_id_posts_id_fk",
      "schema": "public",
      "table": "posts",
      "entityType": "fks"
    },
    {
      "nameExplicit": false,
      "columns": [
        "quote_target_id"
      ],
      "schemaTo": "public",
      "tableTo": "posts",
      "columnsTo": [
        "id"
      ],
      "onUpdate": "NO ACTION",
      "onDelete": "SET NULL",
      "name": "posts_quote_target_id_posts_id_fk",
      "schema": "public",
      "table": "posts",
      "entityType": "fks"
    },
    {
      "nameExplicit": false,
      "columns": [
        "poll_id"
      ],
      "schemaTo": "public",
      "tableTo": "polls",
      "columnsTo": [
        "id"
      ],
      "onUpdate": "NO ACTION",
      "onDelete": "SET NULL",
      "name": "posts_poll_id_polls_id_fk",
      "schema": "public",
      "table": "posts",
      "entityType": "fks"
    },
    {
      "isRlsEnabled": false,
      "name": "reactions",
      "schema": "public",
      "entityType": "tables"
    },
    {
      "type": "uuid",
      "typeSchema": null,
      "notNull": true,
      "dimensions": 0,
      "default": null,
      "generated": null,
      "identity": null,
      "name": "post_id",
      "schema": "public",
      "table": "reactions",
      "entityType": "columns"
    },
    {
      "type": "uuid",
      "typeSchema": null,
      "notNull": true,
      "dimensions": 0,
      "default": null,
      "generated": null,
      "identity": null,
      "name": "account_id",
      "schema": "public",
      "table": "reactions",
      "entityType": "columns"
    },
    {
      "type": "text",
      "typeSchema": null,
      "notNull": true,
      "dimensions": 0,
      "default": null,
      "generated": null,
      "identity": null,
      "name": "emoji",
      "schema": "public",
      "table": "reactions",
      "entityType": "columns"
    },
    {
      "type": "text",
      "typeSchema": null,
      "notNull": false,
      "dimensions": 0,
      "default": null,
      "generated": null,
      "identity": null,
      "name": "custom_emoji",
      "schema": "public",
      "table": "reactions",
      "entityType": "columns"
    },
    {
      "type": "timestamp with time zone",
      "typeSchema": null,
      "notNull": true,
      "dimensions": 0,
      "default": "now()",
      "generated": null,
      "identity": null,
      "name": "created",
      "schema": "public",
      "table": "reactions",
      "entityType": "columns"
    },
    {
      "columns": [
        "post_id",
        "account_id",
        "emoji"
      ],
      "nameExplicit": false,
      "name": "reactions_post_id_account_id_emoji_pk",
      "schema": "public",
      "table": "reactions",
      "entityType": "pks"
    },
    {
      "nameExplicit": false,
      "columns": [
        "post_id"
      ],
      "schemaTo": "public",
      "tableTo": "posts",
      "columnsTo": [
        "id"
      ],
      "onUpdate": "NO ACTION",
      "onDelete": "CASCADE",
      "name": "reactions_post_id_posts_id_fk",
      "schema": "public",
      "table": "reactions",
      "entityType": "fks"
    },
    {
      "nameExplicit": false,
      "columns": [
        "account_id"
      ],
      "schemaTo": "public",
      "tableTo": "accounts",
      "columnsTo": [
        "id"
      ],
      "onUpdate": "NO ACTION",
      "onDelete": "CASCADE",
      "name": "reactions_account_id_accounts_id_fk",
      "schema": "public",
      "table": "reactions",
      "entityType": "fks"
    },
    {
      "values": [
        "Application",
        "Group",
        "Organization",
        "Person",
        "Service"
      ],
      "name": "account_type",
      "schema": "public",
      "entityType": "enums"
    },
    {
      "values": [
        "authorization_code",
        "client_credentials"
      ],
      "name": "grant_type",
      "schema": "public",
      "entityType": "enums"
    },
    {
      "values": [
        "followed",
        "list",
        "none"
      ],
      "name": "list_replies_policy",
      "schema": "public",
      "entityType": "enums"
    },
    {
      "values": [
        "notifications",
        "home"
      ],
      "name": "marker_type",
      "schema": "public",
      "entityType": "enums"
    },
    {
      "values": [
        "Article",
        "Note",
        "Question"
      ],
      "name": "post_type",
      "schema": "public",
      "entityType": "enums"
    },
    {
      "values": [
        "public",
        "unlisted",
        "private",
        "direct"
      ],
      "name": "post_visibility",
      "schema": "public",
      "entityType": "enums"
    },
    {
      "values": [
        "read",
        "read:accounts",
        "read:blocks",
        "read:bookmarks",
        "read:favourites",
        "read:filters",
        "read:follows",
        "read:lists",
        "read:mutes",
        "read:notifications",
        "read:search",
        "read:statuses",
        "write",
        "write:accounts",
        "write:blocks",
        "write:bookmarks",
        "write:conversations",
        "write:favourites",
        "write:filters",
        "write:follows",
        "write:lists",
        "write:media",
        "write:mutes",
        "write:notifications",
        "write:reports",
        "write:statuses",
        "follow",
        "push"
      ],
      "name": "scope",
      "schema": "public",
      "entityType": "enums"
    }
  ],
  "renames": []
}